pacotepypi/modulo.py
pacotepypii-0.0.1.dist-info/LICENSE
pacotepypii-0.0.1.dist-info/METADATA
pacotepypii-0.0.1.dist-info/WHEEL
pacotepypii-0.0.1.dist-info/top_level.txt
pacotepypii-0.0.1.dist-info/RECORD
